Metadata-Version: 2.1
Name: duino-littlefs
Version: 0.0.2
Summary: A duino_cli plugin for working with Arduino LittleFs file systems.
Home-page: https://github.com/dhylands/duino_littlefs
Author: Dave Hylands
Author-email: dhylands@gmail.com
License: MIT
Download-URL: https://github.com/dhylands/duino_littlefs/shell/tarball/v0.0.2
Keywords: cmd cli arduino duino_cli
Platform: UNKNOWN
Classifier: Development Status :: 3 - Alpha
Classifier: Environment :: Console
Classifier: Intended Audience :: Developers
Classifier: License :: OSI Approved :: MIT License
Classifier: Natural Language :: English
Classifier: Operating System :: POSIX :: Linux
Classifier: Programming Language :: Python
Classifier: Programming Language :: Python :: 3
Classifier: Topic :: Software Development :: Embedded Systems
Classifier: Topic :: System :: Shells
Classifier: Topic :: Terminals :: Serial
Classifier: Topic :: Utilities
License-File: LICENSE
